python_mano_wrappers-1.1.1.dist-info/DESCRIPTION.rst
python_mano_wrappers-1.1.1.dist-info/METADATA
python_mano_wrappers-1.1.1.dist-info/RECORD
python_mano_wrappers-1.1.1.dist-info/WHEEL
python_mano_wrappers-1.1.1.dist-info/metadata.json
python_mano_wrappers-1.1.1.dist-info/top_level.txt
tests/osm/__init__.py
tests/osm/config.py
tests/osm/helpers.py
tests/osm/osm_fixture.py
tests/osm/test_admin.py
tests/osm/test_auth.py
tests/osm/test_nsd.py
tests/osm/test_nslcm.py
tests/osm/test_vnfpkgm.py
tests/sonata/__init__.py
tests/sonata/config.py
tests/sonata/helpers.py
tests/sonata/sonata_fixture.py
tests/sonata/test_admin.py
tests/sonata/test_auth.py
tests/sonata/test_database.py
tests/sonata/test_nsd.py
tests/sonata/test_nslcm.py
tests/sonata/test_pishahang.py
tests/sonata/test_sonpackage.py
tests/sonata/test_vnfpkgm.py
wrappers/__init__.py
wrappers/CommonInterface/__init__.py
wrappers/CommonInterface/auth.py
wrappers/CommonInterface/database.py
wrappers/CommonInterface/nsd.py
wrappers/CommonInterface/nsfm.py
wrappers/CommonInterface/nslcm.py
wrappers/CommonInterface/nspm.py
wrappers/CommonInterface/sonpackage.py
wrappers/CommonInterface/vnfpkgm.py
wrappers/OSMClient/__init__.py
wrappers/OSMClient/admin.py
wrappers/OSMClient/auth.py
wrappers/OSMClient/helpers.py
wrappers/OSMClient/nsd.py
wrappers/OSMClient/nsfm.py
wrappers/OSMClient/nslcm.py
wrappers/OSMClient/nspm.py
wrappers/OSMClient/vnfpkgm.py
wrappers/SONATAClient/__init__.py
wrappers/SONATAClient/admin.py
wrappers/SONATAClient/auth.py
wrappers/SONATAClient/database.py
wrappers/SONATAClient/nsd.py
wrappers/SONATAClient/nslcm.py
wrappers/SONATAClient/pishahang.py
wrappers/SONATAClient/sonpackage.py
wrappers/SONATAClient/vnfpkgm.py
