Metadata-Version: 2.0
Name: python-mano-wrappers
Version: 1.1.1
Summary: REST API Wrappers for various MANOs in compliance with ETSI SOL0005
Home-page: https://github.com/CN-UPB/python-mano-wrappers
Author: PG-SCrAMbLE Team WP3
Author-email: ashwin@campus.uni-paderborn.de
License: UNKNOWN
Platform: UNKNOWN
Classifier: Programming Language :: Python :: 3
Classifier: Programming Language :: Python :: 3.7
Requires-Dist: requests
